spycular/__init__.py
spycular/consumer/__init__.py
spycular/consumer/abstract.py
spycular/consumer/virtual_consumer.py
spycular/pointer/__init__.py
spycular/pointer/abstract.py
spycular/pointer/callable_pointer.py
spycular/pointer/class_pointer.py
spycular/pointer/graph/__init__.py
spycular/pointer/graph/abstract.py
spycular/pointer/graph/async_graph.py
spycular/pointer/graph/pointer_node.py
spycular/pointer/graph/state_enum.py
spycular/pointer/object_pointer.py
spycular/pointer/object_pointer.pyx
spycular/producer/__init__.py
spycular/producer/abstract.py
spycular/producer/virtual_producer.py
spycular/puppetry/__init__.py
spycular/puppetry/puppet.py
spycular/puppetry/puppeteer.py
spycular/serde/__init__.py
spycular/serde/capnp/__init__.py
spycular/serde/capnp/deserialize.py
spycular/serde/capnp/numpy/__init__.py
spycular/serde/capnp/numpy/serde.py
spycular/serde/capnp/primitives/__init__.py
spycular/serde/capnp/primitives/serde.py
spycular/serde/capnp/recursive.py
spycular/serde/capnp/recursive_primitives.py
spycular/serde/capnp/schemas/iterable.capnp
spycular/serde/capnp/schemas/kv_iterable.capnp
spycular/serde/capnp/schemas/recursive_serde.capnp
spycular/serde/capnp/serialize.py
spycular/serde/capnp/torch/__init__.py
spycular/serde/capnp/torch/serde.py
spycular/serde/capnp/util.py
spycular/store/__init__.py
spycular/store/abstract.py
spycular/store/virtual_store.py
spycular/utils/graph_view.py
spycular/utils/uuid_gen.c
spycular/utils/uuid_gen.py
spycular/utils/uuid_gen.pyx
spycular-0.1.0.dist-info/LICENSE
spycular-0.1.0.dist-info/METADATA
spycular-0.1.0.dist-info/WHEEL
spycular-0.1.0.dist-info/RECORD
