Metadata-Version: 2.1
Name: spycular
Version: 0.1.0
Summary: Spycular offers an innovative way to use Python libraries remotely through RPC. Inspired by the idea of specular reflection, it provides unparalleled flexibility, allowing you to customize the communication protocol, serialization method, and even the way objects are managed and stored on the remote side.
Home-page: https://github.com/IonesioJunior/Spycular
License: Apache-2.0
Author: Ionesio Junior
Author-email: ionesiojr@gmail.com
Requires-Python: >=3.10,<4.0
Classifier: License :: OSI Approved :: Apache Software License
Classifier: Programming Language :: Python :: 3
Classifier: Programming Language :: Python :: 3.10
Classifier: Programming Language :: Python :: 3.11
Provides-Extra: capnp
Provides-Extra: cython
Provides-Extra: numpy
Provides-Extra: test
Provides-Extra: torch
Requires-Dist: cython (>=3.0.0,<4.0.0) ; extra == "cython"
Requires-Dist: numpy (>=1.24,<2.0) ; extra == "numpy" or extra == "torch"
Requires-Dist: pyarrow (>=11.0.0,<12.0.0) ; extra == "numpy" or extra == "torch"
Requires-Dist: pycapnp (>=1.3.0,<2.0.0) ; extra == "capnp"
Requires-Dist: pydantic (>=2.2.0,<3.0.0)
Requires-Dist: torch (>=2.0.0,!=2.0.1) ; extra == "torch"
Project-URL: Documentation, https://github.com/IonesioJunior/Spycular
Project-URL: Repository, https://github.com/IonesioJunior/Spycular
